[
    { "id": 1, "name": "Akka" },
    { "id": 2, "name": "Anaconda" },
    { "id": 3, "name": "Android Studio" },
    { "id": 4, "name": "Ansible" },
    { "id": 5, "name": "Apache" },
    { "id": 6, "name": "Arch Linux" },
    { "id": 7, "name": "Arduino" },
    { "id": 8, "name": "Atom" },
    { "id": 9, "name": "Babel" },
    { "id": 10, "name": "Behance" },
    { "id": 11, "name": "BitBucket" },
    { "id": 12, "name": "Blender" },
    { "id": 13, "name": "BrowserStack" },
    { "id": 14, "name": "Bulma" },
    { "id": 15, "name": "Bun" },
    { "id": 16, "name": "Cairo Graphics" },
    { "id": 17, "name": "Canva" },
    { "id": 18, "name": "CircleCI" },
    { "id": 19, "name": "CLion" },
    { "id": 20, "name": "CMake" },
    { "id": 21, "name": "CodeIgniter" },
    { "id": 22, "name": "Code Pen" },
    { "id": 23, "name": "Composer" },
    { "id": 24, "name": "Confluence" },
    { "id": 25, "name": "CouchDB" },
    { "id": 26, "name": "DataGrip" },
    { "id": 27, "name": "DataSpell" },
    { "id": 28, "name": "DBeaver" },
    { "id": 29, "name": "Deno" },
    { "id": 30, "name": "Docker" },
    { "id": 31, "name": "Doctrine" },
    { "id": 32, "name": "Drupal" },
    { "id": 33, "name": "Eclipse IDE" },
    { "id": 34, "name": "Elastic Search" },
    { "id": 35, "name": "ESLint" },
    { "id": 36, "name": "Figma" },
    { "id": 37, "name": "FileZilla" },
    { "id": 38, "name": "Flutter" },
    { "id": 39, "name": "Gatsby" },
    { "id": 40, "name": "GCC" },
    { "id": 41, "name": "Gentoo" },
    { "id": 42, "name": "GIMP" },
    { "id": 43, "name": "Git" },
    { "id": 44, "name": "GitBook" },
    { "id": 45, "name": "Git Hub" },
    { "id": 46, "name": "GitLab" },
    { "id": 47, "name": "Gitter" },
    { "id": 48, "name": "Godot Engine" },
    { "id": 49, "name": "GoLand" },
    { "id": 50, "name": "Gradle" },
    { "id": 51, "name": "Grafana" },
    { "id": 52, "name": "Grails" },
    { "id": 53, "name": "Handlebars" },
    { "id": 54, "name": "Hardhat" },
    { "id": 55, "name": "Homebrew" },
    { "id": 56, "name": "IFTTT" },
    { "id": 57, "name": "InfluxDB" },
    { "id": 58, "name": "Inkscape" },
    { "id": 59, "name": "IntelliJ IDEA" },
    { "id": 60, "name": "Ionic" },
    { "id": 61, "name": "Jekyll" },
    { "id": 62, "name": "Jenkins" },
    { "id": 63, "name": "JetBrains" },
    { "id": 64, "name": "Jira" },
    { "id": 65, "name": "JSON" },
    { "id": 66, "name": "Jupyter" },
    { "id": 67, "name": "Kaggle" },
    { "id": 68, "name": "Keras" },
    { "id": 69, "name": "Kubernetes" },
    { "id": 70, "name": "LinkedIn" },
    { "id": 71, "name": "LLVM" },
    { "id": 72, "name": "Autodesk Maya" },
    { "id": 73, "name": "MongoDB" },
    { "id": 74, "name": "Moodle" },
    { "id": 75, "name": "MySQL" },
    { "id": 76, "name": "Nano" },
    { "id": 77, "name": "Node.js" },
    { "id": 78, "name": "PhpStorm" },
    { "id": 79, "name": "Postman" },
    { "id": 80, "name": "Rancher" },
    { "id": 81, "name": "Trello" },
    { "id": 82, "name": "Unity" },
    { "id": 83, "name": "Unreal Engine" },
    { "id": 84, "name": "Visual Studio" },
    { "id": 85, "name": "Visual Studio Code" },
    { "id": 86, "name": "Vite.js" },
    { "id": 87, "name": "Webpack" },
    { "id": 88, "name": "WebStorm" },
    { "id": 89, "name": "WordPress" }
  ]
  